{"field":{"fieldName":"EnglishAssessPercentPassADE","displayLabel":"English Assessment","sourceLayer":"schools","variableType":"MEASURE","metricType":"numeric","metadataCategory":"Outcome","rowCountInScope":8,"nullCount":0,"blankCount":3,"missingCount":3,"missingPct":37.5,"distinctCountNonMissing":4,"numericParseableCount":5,"numericParseablePct":100.0,"preview":"mean=20.20 | median=20.00","flags":["high_missing"]},"variableType":"MEASURE","metricType":"numeric","summaryCards":{"nNumeric":5,"mean":20.2,"median":20.0,"stdDev":1.304,"min":19.0,"max":22.0,"q1":19.0,"q3":21.0,"iqr":2.0,"p01":19.0,"p05":19.0,"p95":21.8,"p99":21.96,"zeroPct":0.0,"negativePct":0.0,"skewness":0.387,"outlierCountIqrRule":0},"coverage":{"nRows":8,"nNull":0,"nBlank":3,"nMissing":3,"nNonMissing":5,"nNumeric":5,"nParseFailures":0},"warnings":["high_missing"],"histogram":[{"startInclusive":19.0,"endExclusive":19.6,"count":2},{"startInclusive":19.6,"endExclusive":20.2,"count":1},{"startInclusive":20.2,"endExclusive":20.8,"count":0},{"startInclusive":20.8,"endExclusive":21.4,"count":1},{"startInclusive":21.4,"endExclusive":22.0,"count":1}],"categoryDistribution":[]}