{"field":{"fieldName":"pct_childrenUnder5BelowPoverty","displayLabel":"Children Under 5 Poverty","sourceLayer":"schools","variableType":"MEASURE","metricType":"numeric","metadataCategory":"Community","rowCountInScope":924,"nullCount":0,"blankCount":11,"missingCount":11,"missingPct":1.2,"distinctCountNonMissing":56,"numericParseableCount":913,"numericParseablePct":100.0,"preview":"mean=14.88 | median=11.00","flags":[]},"variableType":"MEASURE","metricType":"numeric","summaryCards":{"nNumeric":913,"mean":14.883,"median":11.0,"stdDev":13.166,"min":0.0,"max":73.0,"q1":4.0,"q3":23.0,"iqr":19.0,"p01":0.0,"p05":0.0,"p95":41.0,"p99":51.88,"zeroPct":11.9,"negativePct":0.0,"skewness":1.01,"outlierCountIqrRule":10},"coverage":{"nRows":924,"nNull":0,"nBlank":11,"nMissing":11,"nNonMissing":913,"nNumeric":913,"nParseFailures":0},"warnings":["Right-skewed distribution"],"histogram":[{"startInclusive":0.0,"endExclusive":3.8421052631578947,"count":202},{"startInclusive":3.8421052631578947,"endExclusive":7.684210526315789,"count":126},{"startInclusive":7.684210526315789,"endExclusive":11.526315789473685,"count":131},{"startInclusive":11.526315789473685,"endExclusive":15.368421052631579,"count":101},{"startInclusive":15.368421052631579,"endExclusive":19.210526315789473,"count":68},{"startInclusive":19.210526315789473,"endExclusive":23.05263157894737,"count":71},{"startInclusive":23.05263157894737,"endExclusive":26.894736842105264,"count":44},{"startInclusive":26.894736842105264,"endExclusive":30.736842105263158,"count":33},{"startInclusive":30.736842105263158,"endExclusive":34.578947368421055,"count":50},{"startInclusive":34.578947368421055,"endExclusive":38.421052631578945,"count":29},{"startInclusive":38.421052631578945,"endExclusive":42.26315789473684,"count":23},{"startInclusive":42.26315789473684,"endExclusive":46.10526315789474,"count":14},{"startInclusive":46.10526315789474,"endExclusive":49.94736842105263,"count":6},{"startInclusive":49.94736842105263,"endExclusive":53.78947368421053,"count":7},{"startInclusive":53.78947368421053,"endExclusive":57.63157894736842,"count":2},{"startInclusive":57.63157894736842,"endExclusive":61.473684210526315,"count":4},{"startInclusive":61.473684210526315,"endExclusive":65.3157894736842,"count":0},{"startInclusive":65.3157894736842,"endExclusive":69.15789473684211,"count":1},{"startInclusive":69.15789473684211,"endExclusive":73.0,"count":1}],"categoryDistribution":[]}