{"field":{"fieldName":"pct_childrenUnder5BelowPoverty","displayLabel":"Children Under 5 Poverty","sourceLayer":"schools","variableType":"MEASURE","metricType":"numeric","metadataCategory":"Community","rowCountInScope":34,"nullCount":0,"blankCount":1,"missingCount":1,"missingPct":2.9,"distinctCountNonMissing":20,"numericParseableCount":33,"numericParseablePct":100.0,"preview":"mean=23.61 | median=16.00","flags":[]},"variableType":"MEASURE","metricType":"numeric","summaryCards":{"nNumeric":33,"mean":23.606,"median":16.0,"stdDev":21.847,"min":0.0,"max":87.0,"q1":7.0,"q3":39.0,"iqr":32.0,"p01":0.0,"p05":0.0,"p95":63.4,"p99":81.56,"zeroPct":18.2,"negativePct":0.0,"skewness":1.05,"outlierCountIqrRule":0},"coverage":{"nRows":34,"nNull":0,"nBlank":1,"nMissing":1,"nNonMissing":33,"nNumeric":33,"nParseFailures":0},"warnings":["Right-skewed distribution"],"histogram":[{"startInclusive":0.0,"endExclusive":10.875,"count":12},{"startInclusive":10.875,"endExclusive":21.75,"count":6},{"startInclusive":21.75,"endExclusive":32.625,"count":6},{"startInclusive":32.625,"endExclusive":43.5,"count":3},{"startInclusive":43.5,"endExclusive":54.375,"count":3},{"startInclusive":54.375,"endExclusive":65.25,"count":1},{"startInclusive":65.25,"endExclusive":76.125,"count":1},{"startInclusive":76.125,"endExclusive":87.0,"count":1}],"categoryDistribution":[]}