{"field":{"fieldName":"pct_childrenBelowPoverty","displayLabel":"Children Below Poverty","sourceLayer":"schools","variableType":"MEASURE","metricType":"numeric","metadataCategory":"Community","rowCountInScope":46,"nullCount":0,"blankCount":0,"missingCount":0,"missingPct":0.0,"distinctCountNonMissing":23,"numericParseableCount":46,"numericParseablePct":100.0,"preview":"mean=27.80 | median=23.50","flags":[]},"variableType":"MEASURE","metricType":"numeric","summaryCards":{"nNumeric":46,"mean":27.804,"median":23.5,"stdDev":14.91,"min":0.0,"max":64.0,"q1":17.0,"q3":39.0,"iqr":22.0,"p01":3.6,"p05":8.25,"p95":58.75,"p99":63.1,"zeroPct":2.2,"negativePct":0.0,"skewness":0.62,"outlierCountIqrRule":0},"coverage":{"nRows":46,"nNull":0,"nBlank":0,"nMissing":0,"nNonMissing":46,"nNumeric":46,"nParseFailures":0},"warnings":[],"histogram":[{"startInclusive":0.0,"endExclusive":8.0,"count":1},{"startInclusive":8.0,"endExclusive":16.0,"count":7},{"startInclusive":16.0,"endExclusive":24.0,"count":15},{"startInclusive":24.0,"endExclusive":32.0,"count":5},{"startInclusive":32.0,"endExclusive":40.0,"count":7},{"startInclusive":40.0,"endExclusive":48.0,"count":6},{"startInclusive":48.0,"endExclusive":56.0,"count":2},{"startInclusive":56.0,"endExclusive":64.0,"count":3}],"categoryDistribution":[]}