{"field":{"fieldName":"SchoolSizeRange","displayLabel":"School Size","sourceLayer":"school_range_included","variableType":"DIMENSION","metricType":"categorical","metadataCategory":"Characteristic","rowCountInScope":1586,"nullCount":0,"blankCount":0,"missingCount":0,"missingPct":0.0,"distinctCountNonMissing":5,"numericParseableCount":0,"numericParseablePct":0.0,"preview":"mode=Small (458)","flags":[]},"variableType":"DIMENSION","metricType":"categorical","summaryCards":{"nNonMissing":1586,"nMissing":0,"distinctCount":5,"modeValue":"Small","modeCount":458,"modePct":28.9,"top5CoveragePct":100.0,"entropy":2.141},"coverage":{"nRows":1586,"nNull":0,"nBlank":0,"nMissing":0,"nNonMissing":1586,"nNumeric":0,"nParseFailures":1586},"warnings":["Contains mixed values; 1586 non-missing values are non-numeric"],"histogram":[],"categoryDistribution":[{"label":"Small","count":458,"pct":28.9},{"label":"Very Small","count":425,"pct":26.8},{"label":"Medium","count":387,"pct":24.4},{"label":"Large","count":244,"pct":15.4},{"label":"Very Large","count":72,"pct":4.5}]}