{"counties":["Apache","Cochise","Coconino","Gila","Graham","Greenlee","La Paz","Maricopa","Mohave","Navajo","Pima","Pinal","Santa Cruz","Yavapai","Yuma"],"axes":[{"field_name":"AZELLA_PercentProf","label":"AZELLA Assessment","is_default_x":false,"is_default_y":false,"available":true,"availabilityReason":null},{"field_name":"AZELLA_ProfChange","label":"AZELLA Assessment Change","is_default_x":false,"is_default_y":false,"available":true,"availabilityReason":null},{"field_name":"Census_Tract","label":"Census Tract","is_default_x":false,"is_default_y":false,"available":true,"availabilityReason":null},{"field_name":"pct_childrenBelowPoverty","label":"Children Below Poverty","is_default_x":false,"is_default_y":false,"available":true,"availabilityReason":null},{"field_name":"pct_childrenUnder5BelowPoverty","label":"Children Under 5 Poverty","is_default_x":false,"is_default_y":false,"available":true,"availabilityReason":null},{"field_name":"ChronicAbsentChange","label":"Chronic Absent Change","is_default_x":false,"is_default_y":false,"available":true,"availabilityReason":null},{"field_name":"ChronicAbsentPercent","label":"Chronic Absent Percent","is_default_x":false,"is_default_y":false,"available":true,"availabilityReason":null},{"field_name":"estimatedCrimeIndex","label":"Crime Index","is_default_x":false,"is_default_y":false,"available":true,"availabilityReason":null},{"field_name":"DistrictCode","label":"District Code","is_default_x":false,"is_default_y":false,"available":true,"availabilityReason":null},{"field_name":"EL_Count","label":"EL Count","is_default_x":false,"is_default_y":false,"available":true,"availabilityReason":null},{"field_name":"EL_Percent","label":"EL Percentage","is_default_x":false,"is_default_y":false,"available":true,"availabilityReason":null},{"field_name":"EnglishAssessPercentPassADE","label":"English Assess Percent Pass","is_default_x":false,"is_default_y":false,"available":true,"availabilityReason":null},{"field_name":"EnglishAssessChange","label":"English Assessment Change","is_default_x":false,"is_default_y":false,"available":true,"availabilityReason":null},{"field_name":"Enroll1YrChange","label":"Enrollment 1Yr Change","is_default_x":false,"is_default_y":false,"available":true,"availabilityReason":null},{"field_name":"Enroll5YrChange","label":"Enrollment 5Yr Change","is_default_x":false,"is_default_y":false,"available":true,"availabilityReason":null},{"field_name":"Enrollment_ADE_LastYear","label":"Enrollment Last Year","is_default_x":false,"is_default_y":false,"available":true,"availabilityReason":null},{"field_name":"FRL_Percent","label":"Free Reduced Lunch Percent","is_default_x":true,"is_default_y":false,"available":true,"availabilityReason":null},{"field_name":"FRL_Count","label":"FRL Count","is_default_x":false,"is_default_y":false,"available":true,"availabilityReason":null},{"field_name":"GEOID","label":"GEOID","is_default_x":false,"is_default_y":false,"available":true,"availabilityReason":null},{"field_name":"EstimatedIncome_Census","label":"Household Income","is_default_x":false,"is_default_y":false,"available":true,"availabilityReason":null},{"field_name":"pct_householdsMoved","label":"Households Moved","is_default_x":false,"is_default_y":false,"available":true,"availabilityReason":null},{"field_name":"K8AccelerationReadiness","label":"K8 Acceleration","is_default_x":false,"is_default_y":false,"available":true,"availabilityReason":null},{"field_name":"K8ELProficiencyandGrowth","label":"K8 EL Proficiency and Growth","is_default_x":false,"is_default_y":false,"available":true,"availabilityReason":null},{"field_name":"K8GrowthChange","label":"K8 Growth Change","is_default_x":false,"is_default_y":false,"available":true,"availabilityReason":null},{"field_name":"K8Growth","label":"K8 Growth Points","is_default_x":false,"is_default_y":false,"available":true,"availabilityReason":null},{"field_name":"K8ProficiencyChange","label":"K8 Proficiency Change","is_default_x":false,"is_default_y":false,"available":true,"availabilityReason":null},{"field_name":"K8Proficiency","label":"K8 Proficiency Points","is_default_x":false,"is_default_y":false,"available":true,"availabilityReason":null},{"field_name":"K8TotalBonusPoints","label":"K8 Total Bonus Points","is_default_x":false,"is_default_y":false,"available":true,"availabilityReason":null},{"field_name":"K8TotalPercentageEarned","label":"K8 Total Percentage Earned","is_default_x":false,"is_default_y":false,"available":true,"availabilityReason":null},{"field_name":"K8TotalPointsEarned","label":"K8 Total Points Earned","is_default_x":false,"is_default_y":false,"available":true,"availabilityReason":null},{"field_name":"K8TotalPointsEligible","label":"K8 Total Points Eligible","is_default_x":false,"is_default_y":false,"available":true,"availabilityReason":null},{"field_name":"LATITUDE","label":"Latitude","is_default_x":false,"is_default_y":false,"available":true,"availabilityReason":null},{"field_name":"LONGITITUDE","label":"Longitude","is_default_x":false,"is_default_y":false,"available":true,"availabilityReason":null},{"field_name":"MathAssessPercentPassADE","label":"Math Assess Percent Pass","is_default_x":false,"is_default_y":true,"available":true,"availabilityReason":null},{"field_name":"MathAssessChange","label":"Math Assessment Change","is_default_x":false,"is_default_y":false,"available":true,"availabilityReason":null},{"field_name":"pct_peopleBelowPoverty","label":"People Below Poverty","is_default_x":false,"is_default_y":false,"available":true,"availabilityReason":null},{"field_name":"StudentTotal_ADE","label":"School Size","is_default_x":false,"is_default_y":false,"available":true,"availabilityReason":null},{"field_name":"SciAssessPercentPassADE","label":"Science Assess Percent Pass","is_default_x":false,"is_default_y":false,"available":true,"availabilityReason":null},{"field_name":"SciAssessChange","label":"Science Assessment Change","is_default_x":false,"is_default_y":false,"available":true,"availabilityReason":null},{"field_name":"SpendingPerStudent","label":"Spending Per Student","is_default_x":false,"is_default_y":false,"available":true,"availabilityReason":null},{"field_name":"Staff_InexperiencePercent","label":"Staff Inexperience Percent","is_default_x":false,"is_default_y":false,"available":true,"availabilityReason":null},{"field_name":"Staff_NumTotal","label":"Staff Total Count","is_default_x":false,"is_default_y":false,"available":true,"availabilityReason":null},{"field_name":"Enrollment_ADE","label":"Student Enrollment","is_default_x":false,"is_default_y":false,"available":true,"availabilityReason":null},{"field_name":"StudentTeacherRatio","label":"Student Teacher Ratio","is_default_x":false,"is_default_y":false,"available":true,"availabilityReason":null},{"field_name":"Teacher_EmergencyPercent","label":"Teacher Emergency Cert %","is_default_x":false,"is_default_y":false,"available":true,"availabilityReason":null},{"field_name":"Teacher_OutofFieldPercent","label":"Teacher Out of Field Percent","is_default_x":false,"is_default_y":false,"available":true,"availabilityReason":null},{"field_name":"TeacherPay_AZ_SupReport","label":"Teacher Pay","is_default_x":false,"is_default_y":false,"available":true,"availabilityReason":null},{"field_name":"ExpTeacherPay","label":"Teacher Pay - Experienced","is_default_x":false,"is_default_y":false,"available":true,"availabilityReason":null},{"field_name":"NewTeacherPay","label":"Teacher Pay - New","is_default_x":false,"is_default_y":false,"available":true,"availabilityReason":null},{"field_name":"TeacherPay","label":"Teacher Pay Average","is_default_x":false,"is_default_y":false,"available":true,"availabilityReason":null},{"field_name":"TeacherPayProgression","label":"Teacher Pay Progression","is_default_x":false,"is_default_y":false,"available":true,"availabilityReason":null},{"field_name":"Teacher_NumTotal","label":"Teacher Total Count","is_default_x":false,"is_default_y":false,"available":true,"availabilityReason":null},{"field_name":"PercentTeachersIn4thYear","label":"Teachers In 4th Year Percent","is_default_x":false,"is_default_y":false,"available":true,"availabilityReason":null},{"field_name":"FiscalYear","label":"Academic Year","is_default_x":false,"is_default_y":false,"available":false,"availabilityReason":"NON_NUMERIC"},{"field_name":"City_or_County","label":"City","is_default_x":false,"is_default_y":false,"available":false,"availabilityReason":"NON_NUMERIC"},{"field_name":"CountyName","label":"County","is_default_x":false,"is_default_y":false,"available":false,"availabilityReason":"NON_NUMERIC"},{"field_name":"LetterGrade","label":"Letter Grade","is_default_x":false,"is_default_y":false,"available":false,"availabilityReason":"NON_NUMERIC"}]}