{"outliers":[{"schoolCode":91204,"schoolName":"Liberty Traditional Charter School - Saddleback","county":"Cochise","xValue":41.38,"yValue":18.02,"categoryLabel":"0-19","fitted":32.01030484274352,"ciLower":24.31346988528361,"ciUpper":39.707139800203436,"isOutlier":true,"direction":"negative","stdResid":-3.5626329060363155},{"schoolCode":5893,"schoolName":"Mary C  O`Brien Elementary School","county":"Pinal","xValue":63.04,"yValue":26.04,"categoryLabel":"20-29","fitted":39.45022571240061,"ciLower":31.753390754940696,"ciUpper":47.14706066986052,"isOutlier":true,"direction":"negative","stdResid":-3.4149156817803696},{"schoolCode":92866,"schoolName":"BASIS Chandler Primary- South Campus","county":"Maricopa","xValue":78.85,"yValue":31.85,"categoryLabel":"30-39","fitted":44.88074967127774,"ciLower":37.18391471381783,"ciUpper":52.577584628737654,"isOutlier":true,"direction":"negative","stdResid":-3.3182820596861413},{"schoolCode":6152,"schoolName":"O C Johnson School","county":"Yuma","xValue":58.42,"yValue":25.42,"categoryLabel":"20-29","fitted":37.86331738286157,"ciLower":30.166482425401654,"ciUpper":45.56015234032148,"isOutlier":true,"direction":"negative","stdResid":-3.16869235279243},{"schoolCode":1002031,"schoolName":"Premier Prep Online Academy","county":"Maricopa","xValue":25.27,"yValue":14.41,"categoryLabel":"0-19","fitted":26.476734888441786,"ciLower":18.779899930981877,"ciUpper":34.173569845901696,"isOutlier":true,"direction":"negative","stdResid":-3.072795572733844},{"schoolCode":5311,"schoolName":"Kyrene De Los Lagos School","county":"Maricopa","xValue":81.04,"yValue":33.93,"categoryLabel":"30-39","fitted":45.63298543787742,"ciLower":37.93615048041751,"ciUpper":53.329820395337336,"isOutlier":true,"direction":"negative","stdResid":-2.9801667289238116},{"schoolCode":1001860,"schoolName":"SLAM Arizona, Inc.","county":"Maricopa","xValue":60.8,"yValue":50.0,"categoryLabel":"50+","fitted":38.680815613230166,"ciLower":30.983980655770253,"ciUpper":46.37765057069008,"isOutlier":true,"direction":"positive","stdResid":2.88243174248737},{"schoolCode":5547,"schoolName":"Khalsa Montessori Elementary School - Phoenix","county":"Maricopa","xValue":63.6,"yValue":28.39,"categoryLabel":"20-29","fitted":39.64257823719322,"ciLower":31.945743279733307,"ciUpper":47.33941319465313,"isOutlier":true,"direction":"negative","stdResid":-2.8654704780336435},{"schoolCode":80002,"schoolName":"Desert View Middle & High School","county":"Yuma","xValue":57.1,"yValue":26.29,"categoryLabel":"20-29","fitted":37.409915002993266,"ciLower":29.713080045533353,"ciUpper":45.10674996045318,"isOutlier":true,"direction":"negative","stdResid":-2.831687768586315},{"schoolCode":469376,"schoolName":"BASIS Phoenix Primary","county":"Maricopa","xValue":80.35,"yValue":34.35,"categoryLabel":"30-39","fitted":45.395979648400804,"ciLower":37.69914469094089,"ciUpper":53.09281460586072,"isOutlier":true,"direction":"negative","stdResid":-2.812860121143937}]}