{"outliers":[{"schoolCode":79616,"schoolName":"Augustus H. Shaw Montessori","county":"Maricopa","xValue":34.0,"yValue":28.14,"categoryLabel":"25-29","fitted":8.309993565627368,"ciLower":-2.7847162908391585,"ciUpper":19.404703422093895,"isOutlier":true,"direction":"positive","stdResid":3.5031842305201817},{"schoolCode":91422,"schoolName":"Great Hearts Academies - North Phoenix Prep","county":"Maricopa","xValue":8.0,"yValue":0.04,"categoryLabel":"0-9","fitted":18.757456179839163,"ciLower":7.662746323372637,"ciUpper":29.85216603630569,"isOutlier":true,"direction":"negative","stdResid":-3.306640244503761},{"schoolCode":4735,"schoolName":"Tsaile Elementary School","county":"Apache","xValue":38.0,"yValue":23.78,"categoryLabel":"20-24","fitted":6.7026916249793995,"ciLower":-4.392018231487127,"ciUpper":17.797401481445924,"isOutlier":true,"direction":"positive","stdResid":3.0168904683461886},{"schoolCode":92351,"schoolName":"Mesa Center for Success","county":"Maricopa","xValue":8.0,"yValue":1.86,"categoryLabel":"0-9","fitted":18.757456179839163,"ciLower":7.662746323372637,"ciUpper":29.85216603630569,"isOutlier":true,"direction":"negative","stdResid":-2.9851176408350524},{"schoolCode":5666,"schoolName":"Carrillo Intermediate Magnet School","county":"Pima","xValue":27.0,"yValue":27.98,"categoryLabel":"25-29","fitted":11.122771961761313,"ciLower":0.028062105294786477,"ciUpper":22.21748181822784,"isOutlier":true,"direction":"positive","stdResid":2.978010906314097},{"schoolCode":6065,"schoolName":"BASIS Tucson Primary","county":"Pima","xValue":21.0,"yValue":29.87,"categoryLabel":"25-29","fitted":13.533724872733265,"ciLower":2.4390150162667386,"ciUpper":24.62843472919979,"isOutlier":true,"direction":"positive","stdResid":2.885978963278661},{"schoolCode":5972,"schoolName":"Mexicayotl Charter School","county":"Santa Cruz","xValue":31.0,"yValue":24.78,"categoryLabel":"20-24","fitted":9.515470021113345,"ciLower":-1.5792398353531816,"ciUpper":20.61017987757987,"isOutlier":true,"direction":"positive","stdResid":2.696643638786095},{"schoolCode":5381,"schoolName":"Alhambra Traditional School","county":"Maricopa","xValue":18.0,"yValue":30.0,"categoryLabel":"30+","fitted":14.739201328219242,"ciLower":3.6444914717527155,"ciUpper":25.833911184685768,"isOutlier":true,"direction":"positive","stdResid":2.695984463195009},{"schoolCode":1001089,"schoolName":"Maricopa Virtual Academy","county":"Pinal","xValue":8.0,"yValue":3.91,"categoryLabel":"0-9","fitted":18.757456179839163,"ciLower":7.662746323372637,"ciUpper":29.85216603630569,"isOutlier":true,"direction":"negative","stdResid":-2.622963059779639},{"schoolCode":92176,"schoolName":"Mexicayotl Academy","county":"Pima","xValue":40.0,"yValue":20.72,"categoryLabel":"20-24","fitted":5.8990406546554155,"ciLower":-5.195669201811111,"ciUpper":16.99375051112194,"isOutlier":true,"direction":"positive","stdResid":2.6182821085622345}]}