{"science":{"schoolCode":5627,"subject":"Science","expectedValueAvailable":true,"expectedValue":{"schoolName":"Nikolaus Homestead Elementary School","districtName":"Show Low Unified District","county":"Navajo","titleOne":"Yes","modelName":"expected_value_ols","actual":30.0,"expected":41.5355,"residual":-11.5355,"stdResidual":-1.1367,"percentile":10.2,"classification":"as_expected","numberTested":null,"drivers":[{"name":"pct_white","value":0.6475,"contribution":5.9642},{"name":"log_enrollment","value":5.948,"contribution":2.2379},{"name":"pct_low_income","value":0.6214,"contribution":-1.8259}]},"equityGaps":[{"gapLabel":"low_income_vs_all","focalSubgroup":"Income Eligibility 1 and 2","referenceSubgroup":"All Students","focalPercentPassing":25.0,"referencePercentPassing":30.0,"gap":null,"gapAvailable":false,"gapTrendSlope":0.4286,"gapTrendClass":"stable"}],"equityGapCount":1,"modelMetrics":{"evaluationRowCount":758,"baselineRmse":15.520795,"modelRmse":10.148003,"improvementPct":34.616732,"publishable":true},"available":true},"mathematics":{"schoolCode":5627,"subject":"Mathematics","expectedValueAvailable":true,"expectedValue":{"schoolName":"Nikolaus Homestead Elementary School","districtName":"Show Low Unified District","county":"Navajo","titleOne":"Yes","modelName":"expected_value_ols","actual":26.0,"expected":41.748,"residual":-15.748,"stdResidual":-1.293,"percentile":8.7,"classification":"as_expected","numberTested":341,"drivers":[{"name":"pct_white","value":0.6475,"contribution":6.5171},{"name":"pct_hispanic","value":0.2507,"contribution":2.642},{"name":"pct_black","value":0.0,"contribution":1.0349}]},"equityGaps":[{"gapLabel":"hispanic_vs_white","focalSubgroup":"Hispanic or Latino","referenceSubgroup":"White","focalPercentPassing":18.0,"referencePercentPassing":30.0,"gap":null,"gapAvailable":false,"gapTrendSlope":0.9,"gapTrendClass":"stable"},{"gapLabel":"low_income_vs_all","focalSubgroup":"Income Eligibility 1 and 2","referenceSubgroup":"All Students","focalPercentPassing":20.0,"referencePercentPassing":26.0,"gap":null,"gapAvailable":false,"gapTrendSlope":1.0,"gapTrendClass":"stable"}],"equityGapCount":2,"modelMetrics":{"evaluationRowCount":941,"baselineRmse":18.061216,"modelRmse":12.179043,"improvementPct":32.567981,"publishable":true},"available":true},"english-language-arts":{"schoolCode":5627,"subject":"English Language Arts","expectedValueAvailable":true,"expectedValue":{"schoolName":"Nikolaus Homestead Elementary School","districtName":"Show Low Unified District","county":"Navajo","titleOne":"Yes","modelName":"expected_value_ols","actual":34.0,"expected":45.7009,"residual":-11.7009,"stdResidual":-1.2636,"percentile":8.0,"classification":"as_expected","numberTested":340,"drivers":[{"name":"pct_white","value":0.6475,"contribution":7.2829},{"name":"pct_el","value":0.047,"contribution":1.6967},{"name":"pct_low_income","value":0.6214,"contribution":-0.5886}]},"equityGaps":[{"gapLabel":"hispanic_vs_white","focalSubgroup":"Hispanic or Latino","referenceSubgroup":"White","focalPercentPassing":27.0,"referencePercentPassing":38.0,"gap":null,"gapAvailable":false,"gapTrendSlope":-0.7,"gapTrendClass":"stable"},{"gapLabel":"low_income_vs_all","focalSubgroup":"Income Eligibility 1 and 2","referenceSubgroup":"All Students","focalPercentPassing":26.0,"referencePercentPassing":34.0,"gap":null,"gapAvailable":false,"gapTrendSlope":0.0,"gapTrendClass":"stable"}],"equityGapCount":2,"modelMetrics":{"evaluationRowCount":969,"baselineRmse":16.716708,"modelRmse":9.259969,"improvementPct":44.606504,"publishable":true},"available":true}}