{"science":{"schoolCode":89870,"subject":"Science","expectedValueAvailable":false,"expectedValue":null,"equityGaps":[],"equityGapCount":0,"modelMetrics":{"evaluationRowCount":758,"baselineRmse":15.520795,"modelRmse":10.148003,"improvementPct":34.616732,"publishable":true},"available":false,"unavailableReason":"no_advanced_coverage"},"mathematics":{"schoolCode":89870,"subject":"Mathematics","expectedValueAvailable":true,"expectedValue":{"schoolName":"AZ Compass Prep School","districtName":"AZ Compass Schools, Inc.","county":"Maricopa","titleOne":"Yes","modelName":"expected_value_ols","actual":11.0,"expected":27.8457,"residual":-16.8457,"stdResidual":-1.3832,"percentile":7.5,"classification":"as_expected","numberTested":114,"drivers":[{"name":"pct_low_income","value":0.7004,"contribution":-3.5926},{"name":"pct_white","value":0.1049,"contribution":-3.1693},{"name":"pct_black","value":0.2622,"contribution":-3.0372}]},"equityGaps":[],"equityGapCount":0,"modelMetrics":{"evaluationRowCount":941,"baselineRmse":18.061216,"modelRmse":12.179043,"improvementPct":32.567981,"publishable":true},"available":true},"english-language-arts":{"schoolCode":89870,"subject":"English Language Arts","expectedValueAvailable":true,"expectedValue":{"schoolName":"AZ Compass Prep School","districtName":"AZ Compass Schools, Inc.","county":"Maricopa","titleOne":"Yes","modelName":"expected_value_ols","actual":13.0,"expected":33.1824,"residual":-20.1824,"stdResidual":-2.1795,"percentile":1.4,"classification":"underperforming","numberTested":112,"drivers":[{"name":"pct_white","value":0.1049,"contribution":-3.4255},{"name":"pct_low_income","value":0.7004,"contribution":-3.3584},{"name":"pct_swd","value":0.1161,"contribution":2.038}]},"equityGaps":[],"equityGapCount":0,"modelMetrics":{"evaluationRowCount":969,"baselineRmse":16.716708,"modelRmse":9.259969,"improvementPct":44.606504,"publishable":true},"available":true}}