{"english-language-arts":{"schoolCode":91712,"subject":"English Language Arts","expectedValueAvailable":true,"expectedValue":{"schoolName":"George Gervin Prep Academy","districtName":"George Gervin Youth Center, Inc.","county":"Maricopa","titleOne":"Yes","modelName":"expected_value_ols","actual":22.0,"expected":43.6771,"residual":-21.6771,"stdResidual":-2.341,"percentile":1.2,"classification":"underperforming","numberTested":77,"drivers":[{"name":"pct_low_income","value":0.2102,"contribution":13.8356},{"name":"pct_white","value":0.0,"contribution":-5.4949},{"name":"pct_el","value":0.2611,"contribution":-1.9256}]},"equityGaps":[],"equityGapCount":0,"modelMetrics":{"evaluationRowCount":969,"baselineRmse":16.716708,"modelRmse":9.259969,"improvementPct":44.606504,"publishable":true},"available":true},"science":{"schoolCode":91712,"subject":"Science","expectedValueAvailable":false,"expectedValue":null,"equityGaps":[],"equityGapCount":0,"modelMetrics":{"evaluationRowCount":758,"baselineRmse":15.520795,"modelRmse":10.148003,"improvementPct":34.616732,"publishable":true},"available":false,"unavailableReason":"no_advanced_coverage"},"mathematics":{"schoolCode":91712,"subject":"Mathematics","expectedValueAvailable":true,"expectedValue":{"schoolName":"George Gervin Prep Academy","districtName":"George Gervin Youth Center, Inc.","county":"Maricopa","titleOne":"Yes","modelName":"expected_value_ols","actual":16.0,"expected":40.7089,"residual":-24.7089,"stdResidual":-2.0288,"percentile":1.8,"classification":"underperforming","numberTested":77,"drivers":[{"name":"pct_low_income","value":0.2102,"contribution":13.823},{"name":"pct_white","value":0.0,"contribution":-5.0413},{"name":"pct_black","value":0.3631,"contribution":-4.6041}]},"equityGaps":[],"equityGapCount":0,"modelMetrics":{"evaluationRowCount":941,"baselineRmse":18.061216,"modelRmse":12.179043,"improvementPct":32.567981,"publishable":true},"available":true}}